{"page":1,"total":1,"pageSize":24,"tagSlug":"kiron-kher","gifs":[{"id":117,"slug":"when-mother-meet-with-daughter-in-law-for-the-first-time","title":"When mother meet with daughter-in-law for the first time.","title_hi":"जब मां पहली बार बहू के साथ मिलती है।","image_url":"https://raw.githubusercontent.com/askgifdotcom/askgifdotcom.github.io/refs/heads/main/gifs/117.gif","watermarked_url":null,"thumbnail_url":"https://raw.githubusercontent.com/askgifdotcom/askgifdotcom.github.io/refs/heads/main/gifs/thumbnails/when-mother-meet-with-daughter-in-law-for-the-first-time.gif","tags":[{"id":65,"name":"bollywood","name_en":"Bollywood","name_hi":"बॉलीवुड","slug":"bollywood"},{"id":234,"name":"daughter-in-law","name_en":"Daughter In Law","name_hi":"बहू","slug":"daughter-in-law"},{"id":235,"name":"hello","name_en":"Hello","name_hi":"नमस्ते","slug":"hello"},{"id":236,"name":"kiron-kher","name_en":"Kiron Kher","name_hi":"किरण खेर","slug":"kiron-kher"},{"id":237,"name":"wave","name_en":"Wave","name_hi":"लहर","slug":"wave"}]}],"updatedAt":"2026-03-23T09:53:56.449Z"}