{"page":1,"total":1,"pageSize":24,"tagSlug":"pimple","gifs":[{"id":1049,"slug":"when-you-see-a-pimple-on-your-face","title":"When you see a pimple on your face.","title_hi":"जब आप अपने चेहरे पर एक दाना देखते हैं।","image_url":"https://raw.githubusercontent.com/askgifdotcom/askgifdotcom.github.io/refs/heads/main/gifs/1049.gif","watermarked_url":null,"thumbnail_url":"https://raw.githubusercontent.com/askgifdotcom/askgifdotcom.github.io/refs/heads/main/gifs/thumbnails/when-you-see-a-pimple-on-your-face.gif","tags":[{"id":58,"name":"actress","name_en":"Actress","name_hi":"अभिनेत्री","slug":"actress"},{"id":65,"name":"bollywood","name_en":"Bollywood","name_hi":"बॉलीवुड","slug":"bollywood"},{"id":863,"name":"crying","name_en":"Crying","name_hi":"रोना","slug":"crying"},{"id":912,"name":"indian","name_en":"Indian","name_hi":"भारतीय","slug":"indian"},{"id":3708,"name":"manjari-fadnnis","name_en":"Manjari Fadnnis","name_hi":"मंजरी फड्निस","slug":"manjari-fadnnis"},{"id":1957,"name":"mirror","name_en":"Mirror","name_hi":"दर्पण","slug":"mirror"},{"id":3709,"name":"pimple","name_en":"Pimple","name_hi":"पिंपल","slug":"pimple"}]}],"updatedAt":"2026-03-24T05:04:54.060Z"}