{"page":1,"total":1,"pageSize":24,"gifs":[{"id":355,"slug":"phone-manufacturers-after-xiaomi-announced-pocophone","title":"Phone manufacturers after Xiaomi announced Pocophone.","title_hi":"ज़ियामी के बाद फोन निर्माताओं ने पोकोफोन की घोषणा की।","image_url":"https://raw.githubusercontent.com/askgifdotcom/askgifdotcom.github.io/refs/heads/main/gifs/355.gif","watermarked_url":null,"thumbnail_url":"https://raw.githubusercontent.com/askgifdotcom/askgifdotcom.github.io/refs/heads/main/gifs/thumbnails/phone-manufacturers-after-xiaomi-announced-pocophone.gif","tags":[{"id":874,"name":"face-scratch","name_en":"Face Scratch","name_hi":"चेहरे पर खरोंच","slug":"face-scratch"},{"id":258,"name":"jim-carrey","name_en":"Jim Carrey","name_hi":"जिम कैरी","slug":"jim-carrey"},{"id":398,"name":"omg","name_en":"Omg","name_hi":"ओह माय गॉड","slug":"omg"},{"id":875,"name":"poco-f1","name_en":"Poco F1","name_hi":"पोको F1","slug":"poco-f1"},{"id":876,"name":"pocophone","name_en":"Pocophone","name_hi":"पोकोफोन","slug":"pocophone"},{"id":1,"name":"shocked","name_en":"Shocked","name_hi":"शॉक्ड","slug":"shocked"},{"id":877,"name":"xiaomi","name_en":"Xiaomi","name_hi":"शाओमी","slug":"xiaomi"}]}],"personName":"Jim Carrey","personNameHi":null,"updatedAt":"2026-03-26T09:46:02.603Z"}