{"page":1,"total":1,"pageSize":24,"tagSlug":"nick-offerman","gifs":[{"id":408,"slug":"when-the-office-is-freezing-and-no-one-lets-you-adust-the-ac-temperature","title":"When the office is freezing and no one lets you adust the AC temperature!","title_hi":"जब कार्यालय ठंडा हो जाता है और कोई भी आपको एसी तापमान समायोजित करने नहीं देता है!","image_url":"https://raw.githubusercontent.com/askgifdotcom/askgifdotcom.github.io/refs/heads/main/gifs/408.gif","watermarked_url":null,"thumbnail_url":"https://raw.githubusercontent.com/askgifdotcom/askgifdotcom.github.io/refs/heads/main/gifs/thumbnails/when-the-office-is-freezing-and-no-one-lets-you-adust-the-ac-temperature.gif","tags":[{"id":2,"name":"actor","name_en":"Actor","name_hi":"अभिनेता","slug":"actor"},{"id":593,"name":"american","name_en":"American","name_hi":"अमेरिकी","slug":"american"},{"id":1140,"name":"coat","name_en":"Coat","name_hi":"कोट","slug":"coat"},{"id":1141,"name":"cold","name_en":"Cold","name_hi":"ठंड","slug":"cold"},{"id":903,"name":"comedian","name_en":"Comedian","name_hi":"कॉमेडियन","slug":"comedian"},{"id":1142,"name":"desktop","name_en":"Desktop","name_hi":"डेस्कटॉप","slug":"desktop"},{"id":1143,"name":"freezing","name_en":"Freezing","name_hi":"फ्रीज़िंग","slug":"freezing"},{"id":1144,"name":"jacket","name_en":"Jacket","name_hi":"जैकेट","slug":"jacket"},{"id":1145,"name":"nick-offerman","name_en":"Nick Offerman","name_hi":"निक ऑफ़रमैन","slug":"nick-offerman"},{"id":1146,"name":"office-sweater","name_en":"Office Sweater","name_hi":"ऑफिस स्वेटर","slug":"office-sweater"},{"id":1147,"name":"parks-and-recreation","name_en":"Parks And Recreation","name_hi":"पार्क्स एंड रिक्रिएशन","slug":"parks-and-recreation"},{"id":1148,"name":"ron-swanson","name_en":"Ron Swanson","name_hi":"रॉन स्वांसन","slug":"ron-swanson"},{"id":1149,"name":"sweater","name_en":"Sweater","name_hi":"स्वेटर","slug":"sweater"},{"id":1150,"name":"woodworker","name_en":"Woodworker","name_hi":"लकड़हारा","slug":"woodworker"},{"id":909,"name":"writer","name_en":"Writer","name_hi":"लेखक","slug":"writer"}]}],"updatedAt":"2026-03-24T05:03:41.688Z"}