{"id":"ahg9qif481ta","gif_id":1447,"gif_title":"Me trying to understand the vaccination rollout strategy.","gif_url":"https://gif.askgif.com/gifs/1447.gif","thumbnail_url":"https://raw.githubusercontent.com/askgifdotcom/askgifdotcom.github.io/refs/heads/main/gifs/thumbnails/me-trying-to-understand-the-vaccination-rollout-strategy.gif","sender_name":"Sumit Chourasia","message":"Thinking on how we can optimize the server and db performance.","created_at":"2026-03-25T07:07:05.177Z","expires_at":"2026-04-24T07:07:05.177Z"}