{"page":1,"total":1,"pageSize":24,"tagSlug":"tamil","gifs":[{"id":887,"slug":"when-you-find-someone-else-is-wearing-the-same-dress-as-yours","title":"When you find someone else is wearing the same dress as yours.","title_hi":"जब आप पाते हैं कि कोई और आपकी जैसी पोशाक पहने हुए है।","image_url":"https://raw.githubusercontent.com/askgifdotcom/askgifdotcom.github.io/refs/heads/main/gifs/887.gif","watermarked_url":null,"thumbnail_url":"https://raw.githubusercontent.com/askgifdotcom/askgifdotcom.github.io/refs/heads/main/gifs/thumbnails/when-you-find-someone-else-is-wearing-the-same-dress-as-yours.gif","tags":[{"id":58,"name":"actress","name_en":"Actress","name_hi":"अभिनेत्री","slug":"actress"},{"id":3182,"name":"amazed","name_en":"Amazed","name_hi":"हैरान","slug":"amazed"},{"id":3380,"name":"asin-thottumkal","name_en":"Asin Thottumkal","name_hi":"असिन थोट्टुमकल","slug":"asin-thottumkal"},{"id":65,"name":"bollywood","name_en":"Bollywood","name_hi":"बॉलीवुड","slug":"bollywood"},{"id":3381,"name":"ghajini","name_en":"Ghajini","name_hi":"घजिनी","slug":"ghajini"},{"id":912,"name":"indian","name_en":"Indian","name_hi":"भारतीय","slug":"indian"},{"id":3382,"name":"open-mouth","name_en":"Open Mouth","name_hi":"खुला मुँह","slug":"open-mouth"},{"id":1,"name":"shocked","name_en":"Shocked","name_hi":"शॉक्ड","slug":"shocked"},{"id":3383,"name":"tamil","name_en":"Tamil","name_hi":"तमिल","slug":"tamil"},{"id":3189,"name":"turn","name_en":"Turn","name_hi":"बदलाव","slug":"turn"},{"id":3384,"name":"turn-around","name_en":"Turn Around","name_hi":"घूमना","slug":"turn-around"}]}],"updatedAt":"2026-03-23T10:01:29.028Z"}