{"page":1,"total":1,"pageSize":24,"tagSlug":"elated","gifs":[{"id":194,"slug":"when-you-get-free-dhaniya-and-mirchi-with-the-vegetables","title":"When you get free dhaniya and mirchi with the vegetables.","title_hi":"जब आप सब्जियों के साथ मुक्त धनीया और मिर्च प्राप्त करते हैं।","image_url":"https://raw.githubusercontent.com/askgifdotcom/askgifdotcom.github.io/refs/heads/main/gifs/194.gif","watermarked_url":null,"thumbnail_url":"https://raw.githubusercontent.com/askgifdotcom/askgifdotcom.github.io/refs/heads/main/gifs/thumbnails/when-you-get-free-dhaniya-and-mirchi-with-the-vegetables.gif","tags":[{"id":411,"name":"beyonce","name_en":"Beyonce","name_hi":"बियॉन्से","slug":"beyonce"},{"id":412,"name":"elated","name_en":"Elated","name_hi":"उत्साहित","slug":"elated"},{"id":413,"name":"free","name_en":"Free","name_hi":"मुक्त","slug":"free"},{"id":8,"name":"happy","name_en":"Happy","name_hi":"खुश","slug":"happy"}]}],"updatedAt":"2026-03-23T09:50:32.069Z"}