{"page":1,"total":2,"pageSize":24,"tagSlug":"do-whatever-you-want","gifs":[{"id":1350,"slug":"dead-people-dont-want-anything-its-one-of-the-benefits-of-being-dead","title":"Dead people don't want anything, it's one of the benefits of being dead.","title_hi":"मृत लोग कुछ भी नहीं चाहते हैं, यह मृत होने के लाभों में से एक है।","image_url":"https://raw.githubusercontent.com/askgifdotcom/askgifdotcom.github.io/refs/heads/main/gifs/1350.gif","watermarked_url":null,"thumbnail_url":"https://raw.githubusercontent.com/askgifdotcom/askgifdotcom.github.io/refs/heads/main/gifs/thumbnails/dead-people-dont-want-anything-its-one-of-the-benefits-of-being-dead.gif","tags":[{"id":955,"name":"dead","name_en":"Dead","name_hi":"मरा","slug":"dead"},{"id":4142,"name":"do-whatever-you-want","name_en":"Do Whatever You Want","name_hi":"जो चाहो करो","slug":"do-whatever-you-want"},{"id":956,"name":"i-am-dead","name_en":"I Am Dead","name_hi":"मैं मरा हूँ","slug":"i-am-dead"},{"id":452,"name":"i-dont-care","name_en":"I Dont Care","name_hi":"मुझे परवाह नहीं","slug":"i-dont-care"},{"id":3145,"name":"i-dont-give-a-fuck","name_en":"I Dont Give A Fuck","name_hi":"मुझे परवाह नहीं","slug":"i-dont-give-a-fuck"},{"id":1407,"name":"quotes","name_en":"Quotes","name_hi":"उद्धरण","slug":"quotes"}]},{"id":1298,"slug":"when-your-friend-is-not-listening-to-you-at-all","title":"When your friend is not listening to you at all.","title_hi":"जब आपका दोस्त आपकी बिल्कुल नहीं सुन रहा हो।","image_url":"https://raw.githubusercontent.com/askgifdotcom/askgifdotcom.github.io/refs/heads/main/gifs/1298.gif","watermarked_url":null,"thumbnail_url":"https://raw.githubusercontent.com/askgifdotcom/askgifdotcom.github.io/refs/heads/main/gifs/thumbnails/when-your-friend-is-not-listening-to-you-at-all.gif","tags":[{"id":4141,"name":"big-bang-theory","name_en":"Big Bang Theory","name_hi":"बिग बैंग थ्योरी","slug":"big-bang-theory"},{"id":3004,"name":"cannot-believe","name_en":"Cannot Believe","name_hi":"विश्वास नहीं होता","slug":"cannot-believe"},{"id":4142,"name":"do-whatever-you-want","name_en":"Do Whatever You Want","name_hi":"जो चाहो करो","slug":"do-whatever-you-want"},{"id":4143,"name":"kaley-cuoco","name_en":"Kaley Cuoco","name_hi":"काले Cuoco","slug":"kaley-cuoco"},{"id":3531,"name":"leave-it","name_en":"Leave It","name_hi":"छोड़ दो","slug":"leave-it"},{"id":107,"name":"the-big-bang-theory","name_en":"The Big Bang Theory","name_hi":"द बिग बैंग थ्योरी","slug":"the-big-bang-theory"},{"id":3133,"name":"whatever","name_en":"Whatever","name_hi":"जो भी","slug":"whatever"}]}],"updatedAt":"2026-03-24T04:54:49.009Z"}