{"page":1,"total":1,"pageSize":24,"tagSlug":"i-hear-nothing","gifs":[{"id":499,"slug":"when-your-mother-starts-asking-why-study-folder-is-of-290-gb-and-hidden","title":"When your mother starts asking why study folder is of 290 GB and hidden?","title_hi":"जब आपकी माँ पूछने लगती है कि अध्ययन फ़ोल्डर 290 जीबी और छिपा हुआ क्यों है?","image_url":"https://raw.githubusercontent.com/askgifdotcom/askgifdotcom.github.io/refs/heads/main/gifs/499.gif","watermarked_url":null,"thumbnail_url":"https://raw.githubusercontent.com/askgifdotcom/askgifdotcom.github.io/refs/heads/main/gifs/thumbnails/when-your-mother-starts-asking-why-study-folder-is-of-290-gb-and-hidden.gif","tags":[{"id":430,"name":"afraid","name_en":"Afraid","name_hi":"डर","slug":"afraid"},{"id":95,"name":"bluff","name_en":"Bluff","name_hi":"धोखा","slug":"bluff"},{"id":1610,"name":"fireman","name_en":"Fireman","name_hi":"फायरमैन","slug":"fireman"},{"id":1611,"name":"i-hear-nothing","name_en":"I Hear Nothing","name_hi":"मुझे कुछ नहीं सुनाई देता","slug":"i-hear-nothing"},{"id":1612,"name":"i-know-nothing","name_en":"I Know Nothing","name_hi":"मुझे कुछ नहीं पता","slug":"i-know-nothing"},{"id":1613,"name":"i-see-nothing","name_en":"I See Nothing","name_hi":"मुझे कुछ नहीं दिखता","slug":"i-see-nothing"},{"id":893,"name":"no-idea","name_en":"No Idea","name_hi":"कोई आइडिया नहीं","slug":"no-idea"},{"id":1614,"name":"porn","name_en":"Porn","name_hi":"पोर्न","slug":"porn"},{"id":1226,"name":"run-away","name_en":"Run Away","name_hi":"भाग जाना","slug":"run-away"},{"id":432,"name":"scared","name_en":"Scared","name_hi":"डर","slug":"scared"},{"id":1615,"name":"study-folder","name_en":"Study Folder","name_hi":"स्टडी फोल्डर","slug":"study-folder"}]}],"updatedAt":"2026-03-24T04:59:05.011Z"}