{"page":1,"total":2,"pageSize":24,"tagSlug":"too-much","gifs":[{"id":1333,"slug":"oh-i-love-her-too-much","title":"Oh, I love her too much!","title_hi":"ओह, मैं उससे बहुत प्यार करता हूँ!","image_url":"https://raw.githubusercontent.com/askgifdotcom/askgifdotcom.github.io/refs/heads/main/gifs/1333.gif","watermarked_url":null,"thumbnail_url":"https://raw.githubusercontent.com/askgifdotcom/askgifdotcom.github.io/refs/heads/main/gifs/thumbnails/oh-i-love-her-too-much.gif","tags":[{"id":311,"name":"bed","name_en":"Bed","name_hi":"बिस्तर","slug":"bed"},{"id":3035,"name":"bed-time","name_en":"Bed Time","name_hi":"सोने का समय","slug":"bed-time"},{"id":211,"name":"i-love-you","name_en":"I Love You","name_hi":"मैं तुमसे प्यार करता हूँ","slug":"i-love-you"},{"id":3172,"name":"in-love","name_en":"In Love","name_hi":"प्यार में","slug":"in-love"},{"id":184,"name":"love","name_en":"Love","name_hi":"प्यार","slug":"love"},{"id":2292,"name":"lover","name_en":"Lover","name_hi":"प्रेमी","slug":"lover"},{"id":2513,"name":"think","name_en":"Think","name_hi":"सोचो","slug":"think"},{"id":24,"name":"thinking","name_en":"Thinking","name_hi":"सोचना","slug":"thinking"},{"id":3177,"name":"thinking-of-you","name_en":"Thinking Of You","name_hi":"तेरे बारे में सोच रहा हूँ","slug":"thinking-of-you"},{"id":2289,"name":"too-much","name_en":"Too Much","name_hi":"बहुत ज्यादा","slug":"too-much"},{"id":2181,"name":"true-love","name_en":"True Love","name_hi":"सच्चा प्यार","slug":"true-love"}]},{"id":631,"slug":"when-your-parents-praise-your-sibling-more-than-you","title":"When your parents praise your sibling more than you.","title_hi":"जब आपके माता-पिता आपसे ज्यादा आपके भाई-बहन की तारीफ करते हैं।","image_url":"https://raw.githubusercontent.com/askgifdotcom/askgifdotcom.github.io/refs/heads/main/gifs/631.gif","watermarked_url":null,"thumbnail_url":"https://raw.githubusercontent.com/askgifdotcom/askgifdotcom.github.io/refs/heads/main/gifs/thumbnails/when-your-parents-praise-your-sibling-more-than-you.gif","tags":[{"id":2282,"name":"bbcan","name_en":"Bbcan","name_hi":"बीबीकैन","slug":"bbcan"},{"id":1801,"name":"big-brother","name_en":"Big Brother","name_hi":"बिग ब्रदर","slug":"big-brother"},{"id":2283,"name":"big-brother-canada","name_en":"Big Brother Canada","name_hi":"बिग ब्रदर कनाडा","slug":"big-brother-canada"},{"id":804,"name":"canadian","name_en":"Canadian","name_hi":"कनाडाई","slug":"canadian"},{"id":2284,"name":"chelsea-bird","name_en":"Chelsea Bird","name_hi":"चेल्सी बर्ड","slug":"chelsea-bird"},{"id":2285,"name":"its-too-much","name_en":"Its Too Much","name_hi":"बहुत ज्यादा","slug":"its-too-much"},{"id":1237,"name":"jealous","name_en":"Jealous","name_hi":"जलन","slug":"jealous"},{"id":2286,"name":"radio-host","name_en":"Radio Host","name_hi":"रेडियो होस्ट","slug":"radio-host"},{"id":2287,"name":"radio-jockey","name_en":"Radio Jockey","name_hi":"रेडियो जॉकी","slug":"radio-jockey"},{"id":2288,"name":"rj","name_en":"Rj","name_hi":"आरजे","slug":"rj"},{"id":695,"name":"sibling-rivalry","name_en":"Sibling Rivalry","name_hi":"भाई-बहन की दुश्मनी","slug":"sibling-rivalry"},{"id":516,"name":"siblings","name_en":"Siblings","name_hi":"भाई-बहन","slug":"siblings"},{"id":2289,"name":"too-much","name_en":"Too Much","name_hi":"बहुत ज्यादा","slug":"too-much"}]}],"updatedAt":"2026-03-23T08:58:50.340Z"}