{"page":1,"total":2,"pageSize":24,"tagSlug":"barbara-palvin","gifs":[{"id":1488,"slug":"a-woman-poses-confidently-in-lingerie-showcasing-her-style-and-beauty-1774502632356","title":"A woman poses confidently in lingerie, showcasing her style and beauty.","title_hi":"एक महिला ने लिंगेरी में आत्मविश्वास से पोज़ दिया, अपनी शैली और सुंदरता को प्रदर्शित किया।","image_url":"https://raw.githubusercontent.com/askgifdotcom/askgifdotcom.github.io/refs/heads/main/gifs/1488.gif","watermarked_url":null,"thumbnail_url":"https://raw.githubusercontent.com/askgifdotcom/askgifdotcom.github.io/refs/heads/main/gifs/thumbnails/1488.gif","tags":[{"id":22087,"name":"barbara-palvin","name_en":null,"name_hi":null,"slug":"barbara-palvin"},{"id":1411,"name":"beauty","name_en":"Beauty","name_hi":"सुंदरता","slug":"beauty"},{"id":4159,"name":"confidence","name_en":"Confidence","name_hi":"आत्मविश्वास","slug":"confidence"},{"id":2478,"name":"lingerie","name_en":"Lingerie","name_hi":"अंडरवियर","slug":"lingerie"},{"id":17986,"name":"style","name_en":"Style","name_hi":"शैली","slug":"style"},{"id":17982,"name":"trending","name_en":"Trending","name_hi":"ट्रेंडिंग","slug":"trending"}]},{"id":1487,"slug":"when-you-realize-sunscreen-is-not-just-for-show-1774497324571","title":"When you realize sunscreen is not just for show!","title_hi":"जब आपको एहसास होता है कि सूर्य क्रीम सिर्फ दिखावे के लिए नहीं है!","image_url":"https://raw.githubusercontent.com/askgifdotcom/askgifdotcom.github.io/refs/heads/main/gifs/1487.gif","watermarked_url":null,"thumbnail_url":"https://raw.githubusercontent.com/askgifdotcom/askgifdotcom.github.io/refs/heads/main/gifs/thumbnails/1487.gif","tags":[{"id":22087,"name":"barbara-palvin","name_en":null,"name_hi":null,"slug":"barbara-palvin"},{"id":442,"name":"beach","name_en":"Beach","name_hi":"समुद्र तट","slug":"beach"},{"id":2726,"name":"fashion","name_en":"Fashion","name_hi":"फैशन","slug":"fashion"},{"id":3358,"name":"fun","name_en":"Fun","name_hi":"मज़ा","slug":"fun"},{"id":300,"name":"summer","name_en":"Summer","name_hi":"गर्मी","slug":"summer"},{"id":1068,"name":"vacation","name_en":"Vacation","name_hi":"छुट्टी","slug":"vacation"}]}],"updatedAt":"2026-03-26T05:24:07.518Z"}