{"page":1,"total":1,"pageSize":24,"tagSlug":"hooray","gifs":[{"id":677,"slug":"when-you-pass-an-exam-without-studying-anything","title":"When you pass an exam without studying anything.","title_hi":"जब आप बिना कुछ पढ़े एक परीक्षा पास कर लेते हैं।","image_url":"https://raw.githubusercontent.com/askgifdotcom/askgifdotcom.github.io/refs/heads/main/gifs/677.gif","watermarked_url":null,"thumbnail_url":"https://raw.githubusercontent.com/askgifdotcom/askgifdotcom.github.io/refs/heads/main/gifs/thumbnails/when-you-pass-an-exam-without-studying-anything.gif","tags":[{"id":593,"name":"american","name_en":"American","name_hi":"अमेरिकी","slug":"american"},{"id":2514,"name":"ecstatic","name_en":"Ecstatic","name_hi":"उत्साहित","slug":"ecstatic"},{"id":240,"name":"exam","name_en":"Exam","name_hi":"परीक्षा","slug":"exam"},{"id":1163,"name":"examination","name_en":"Examination","name_hi":"परीक्षा","slug":"examination"},{"id":191,"name":"excited","name_en":"Excited","name_hi":"उत्साहित","slug":"excited"},{"id":2515,"name":"exhilarated","name_en":"Exhilarated","name_hi":"खुश","slug":"exhilarated"},{"id":8,"name":"happy","name_en":"Happy","name_hi":"खुश","slug":"happy"},{"id":2516,"name":"hooray","name_en":"Hooray","name_hi":"हुर्रे","slug":"hooray"},{"id":2517,"name":"on-cloud-nine","name_en":"On Cloud Nine","name_hi":"आसमान में","slug":"on-cloud-nine"},{"id":2518,"name":"overjoyed","name_en":"Overjoyed","name_hi":"अत्यधिक खुश","slug":"overjoyed"},{"id":2519,"name":"pitbull","name_en":"Pitbull","name_hi":"पिटबुल","slug":"pitbull"},{"id":256,"name":"singer","name_en":"Singer","name_hi":"गायक","slug":"singer"},{"id":1459,"name":"singer-songwriter","name_en":"Singer Songwriter","name_hi":"गायक-गीतकार","slug":"singer-songwriter"},{"id":2520,"name":"success","name_en":"Success","name_hi":"सफलता","slug":"success"},{"id":2521,"name":"thrilled","name_en":"Thrilled","name_hi":"उत्साहित","slug":"thrilled"},{"id":2522,"name":"yay","name_en":"Yay","name_hi":"याय","slug":"yay"}]}],"updatedAt":"2026-03-24T04:58:40.181Z"}