{"page":1,"total":4,"pageSize":24,"tagSlug":"awake","gifs":[{"id":1368,"slug":"wake-up-its-medication-time","title":"Wake up, It's medication time.","title_hi":"जागो, दवा का समय है।","image_url":"https://raw.githubusercontent.com/askgifdotcom/askgifdotcom.github.io/refs/heads/main/gifs/1368.gif","watermarked_url":null,"thumbnail_url":"https://raw.githubusercontent.com/askgifdotcom/askgifdotcom.github.io/refs/heads/main/gifs/thumbnails/wake-up-its-medication-time.gif","tags":[{"id":2937,"name":"awake","name_en":"Awake","name_hi":"जागना","slug":"awake"},{"id":2938,"name":"i-am-awake","name_en":"I Am Awake","name_hi":"मैं जागा हूँ","slug":"i-am-awake"},{"id":2102,"name":"medicine","name_en":"Medicine","name_hi":"दवाई","slug":"medicine"},{"id":4133,"name":"tooth-brush","name_en":"Tooth Brush","name_hi":"दांतों का ब्रश","slug":"tooth-brush"},{"id":3065,"name":"wake-up","name_en":"Wake Up","name_hi":"जागो","slug":"wake-up"},{"id":921,"name":"wide-awake","name_en":"Wide Awake","name_hi":"चेतन","slug":"wide-awake"}]},{"id":1176,"slug":"when-you-are-not-able-to-sleep-at-night","title":"When you are not able to sleep at night.","title_hi":"जब आप रात में सो नहीं पा रहे हैं।","image_url":"https://raw.githubusercontent.com/askgifdotcom/askgifdotcom.github.io/refs/heads/main/gifs/1176.gif","watermarked_url":null,"thumbnail_url":"https://raw.githubusercontent.com/askgifdotcom/askgifdotcom.github.io/refs/heads/main/gifs/thumbnails/when-you-are-not-able-to-sleep-at-night.gif","tags":[{"id":58,"name":"actress","name_en":"Actress","name_hi":"अभिनेत्री","slug":"actress"},{"id":2937,"name":"awake","name_en":"Awake","name_hi":"जागना","slug":"awake"},{"id":311,"name":"bed","name_en":"Bed","name_hi":"बिस्तर","slug":"bed"},{"id":3035,"name":"bed-time","name_en":"Bed Time","name_hi":"सोने का समय","slug":"bed-time"},{"id":5,"name":"hollywood","name_en":"Hollywood","name_hi":"हॉलीवुड","slug":"hollywood"},{"id":2938,"name":"i-am-awake","name_en":"I Am Awake","name_hi":"मैं जागा हूँ","slug":"i-am-awake"},{"id":3905,"name":"lucy-fry","name_en":"Lucy Fry","name_hi":"लुसी फ्राई","slug":"lucy-fry"}]},{"id":802,"slug":"the-coffee-i-need-in-the-morning","title":"The coffee I need in the morning.","title_hi":"सुबह मुझे जो कॉफी चाहिए।","image_url":"https://raw.githubusercontent.com/askgifdotcom/askgifdotcom.github.io/refs/heads/main/gifs/802.gif","watermarked_url":null,"thumbnail_url":"https://raw.githubusercontent.com/askgifdotcom/askgifdotcom.github.io/refs/heads/main/gifs/thumbnails/the-coffee-i-need-in-the-morning.gif","tags":[{"id":2937,"name":"awake","name_en":"Awake","name_hi":"जागना","slug":"awake"},{"id":1666,"name":"coffee","name_en":"Coffee","name_hi":"कॉफी","slug":"coffee"},{"id":2279,"name":"dozing","name_en":"Dozing","name_hi":"नींद में","slug":"dozing"},{"id":3061,"name":"drown","name_en":"Drown","name_hi":"ड्रोन","slug":"drown"},{"id":114,"name":"good-morning","name_en":"Good Morning","name_hi":"शुभ प्रभात","slug":"good-morning"},{"id":187,"name":"lazy","name_en":"Lazy","name_hi":"आलसी","slug":"lazy"},{"id":3062,"name":"morning-brew","name_en":"Morning Brew","name_hi":"सुबह की चाय","slug":"morning-brew"},{"id":3063,"name":"morning-coffee","name_en":"Morning Coffee","name_hi":"सुबह की कॉफी","slug":"morning-coffee"},{"id":3064,"name":"pour","name_en":"Pour","name_hi":"डालना","slug":"pour"},{"id":204,"name":"sleepy","name_en":"Sleepy","name_hi":"नींद में","slug":"sleepy"},{"id":188,"name":"tired","name_en":"Tired","name_hi":"थका हुआ","slug":"tired"},{"id":3065,"name":"wake-up","name_en":"Wake Up","name_hi":"जागो","slug":"wake-up"}]},{"id":772,"slug":"me-during-the-early-morning-meetings","title":"Me during the early morning meetings.","title_hi":"सुबह की बैठकों के दौरान मुझे।","image_url":"https://raw.githubusercontent.com/askgifdotcom/askgifdotcom.github.io/refs/heads/main/gifs/772.gif","watermarked_url":null,"thumbnail_url":"https://raw.githubusercontent.com/askgifdotcom/askgifdotcom.github.io/refs/heads/main/gifs/thumbnails/me-during-the-early-morning-meetings.gif","tags":[{"id":2936,"name":"anna","name_en":"Anna","name_hi":"अन्ना","slug":"anna"},{"id":2937,"name":"awake","name_en":"Awake","name_hi":"जागना","slug":"awake"},{"id":282,"name":"cartoon","name_en":"Cartoon","name_hi":"कार्टून","slug":"cartoon"},{"id":1984,"name":"disney","name_en":"Disney","name_hi":"डिज़्नी","slug":"disney"},{"id":2279,"name":"dozing","name_en":"Dozing","name_hi":"नींद में","slug":"dozing"},{"id":1661,"name":"frozen","name_en":"Frozen","name_hi":"जमी हुई","slug":"frozen"},{"id":2938,"name":"i-am-awake","name_en":"I Am Awake","name_hi":"मैं जागा हूँ","slug":"i-am-awake"},{"id":1432,"name":"kristen-bell","name_en":"Kristen Bell","name_hi":"क्रिस्टन बेल","slug":"kristen-bell"},{"id":2939,"name":"meeting","name_en":"Meeting","name_hi":"बैठक","slug":"meeting"},{"id":164,"name":"movie","name_en":"Movie","name_hi":"फिल्म","slug":"movie"},{"id":122,"name":"office","name_en":"Office","name_hi":"ऑफिस","slug":"office"},{"id":2940,"name":"princess-anna","name_en":"Princess Anna","name_hi":"राजकुमारी अन्ना","slug":"princess-anna"},{"id":204,"name":"sleepy","name_en":"Sleepy","name_hi":"नींद में","slug":"sleepy"},{"id":1679,"name":"team-meeting","name_en":"Team Meeting","name_hi":"टीम मीटिंग","slug":"team-meeting"}]}],"updatedAt":"2026-03-23T08:11:48.523Z"}