{"id":1175,"slug":"this-is-how-i-do-exercise-in-the-kitchen","title":"This is how I do exercise in the kitchen.","title_hi":"इसी तरह से मैं किचन में एक्सरसाइज करती हूं।","image_url":"https://raw.githubusercontent.com/askgifdotcom/askgifdotcom.github.io/refs/heads/main/gifs/1175.gif","watermarked_url":null,"thumbnail_url":"https://raw.githubusercontent.com/askgifdotcom/askgifdotcom.github.io/refs/heads/main/gifs/thumbnails/this-is-how-i-do-exercise-in-the-kitchen.gif","status":"published","language":"en","emotion_tags":["chaotic","relatable"],"view_count":0,"date_created":"2020-04-28T09:17:50.969Z","gif_tags":[{"tags":{"id":58,"name":"actress","name_en":"Actress","name_hi":"अभिनेत्री","slug":"actress"}},{"tags":{"id":1505,"name":"enjoy","name_en":"Enjoy","name_hi":"आनंद लें","slug":"enjoy"}},{"tags":{"id":129,"name":"exercise","name_en":"Exercise","name_hi":"व्यायाम","slug":"exercise"}},{"tags":{"id":700,"name":"fitness","name_en":"Fitness","name_hi":"फिटनेस","slug":"fitness"}},{"tags":{"id":130,"name":"gym","name_en":"Gym","name_hi":"जिम","slug":"gym"}},{"tags":{"id":5,"name":"hollywood","name_en":"Hollywood","name_hi":"हॉलीवुड","slug":"hollywood"}},{"tags":{"id":3903,"name":"kitchen","name_en":"Kitchen","name_hi":"रसोई","slug":"kitchen"}},{"tags":{"id":3904,"name":"laura-vandervoort","name_en":"Laura Vandervoort","name_hi":"लौरा वेंडरवॉर्ट","slug":"laura-vandervoort"}},{"tags":{"id":185,"name":"moment","name_en":"Moment","name_hi":"क्षण","slug":"moment"}}],"tags":[{"id":58,"name":"actress","name_en":"Actress","name_hi":"अभिनेत्री","slug":"actress"},{"id":1505,"name":"enjoy","name_en":"Enjoy","name_hi":"आनंद लें","slug":"enjoy"},{"id":129,"name":"exercise","name_en":"Exercise","name_hi":"व्यायाम","slug":"exercise"},{"id":700,"name":"fitness","name_en":"Fitness","name_hi":"फिटनेस","slug":"fitness"},{"id":130,"name":"gym","name_en":"Gym","name_hi":"जिम","slug":"gym"},{"id":5,"name":"hollywood","name_en":"Hollywood","name_hi":"हॉलीवुड","slug":"hollywood"},{"id":3903,"name":"kitchen","name_en":"Kitchen","name_hi":"रसोई","slug":"kitchen"},{"id":3904,"name":"laura-vandervoort","name_en":"Laura Vandervoort","name_hi":"लौरा वेंडरवॉर्ट","slug":"laura-vandervoort"},{"id":185,"name":"moment","name_en":"Moment","name_hi":"क्षण","slug":"moment"}],"updatedAt":"2026-03-23T09:47:17.719Z"}