{"id":1394,"slug":"im-not-crying","title":"I'm not crying.","title_hi":"मैं रो नहीं रहा हूं।","image_url":"https://raw.githubusercontent.com/askgifdotcom/askgifdotcom.github.io/refs/heads/main/gifs/1394.gif","watermarked_url":null,"thumbnail_url":"https://raw.githubusercontent.com/askgifdotcom/askgifdotcom.github.io/refs/heads/main/gifs/thumbnails/im-not-crying.gif","status":"published","language":"en","emotion_tags":[],"view_count":0,"date_created":"2020-08-17T09:25:47.235Z","gif_tags":[{"tags":{"id":862,"name":"break-up","name_en":"Break Up","name_hi":"ब्रेकअप","slug":"break-up"}},{"tags":{"id":10,"name":"cry","name_en":"Cry","name_hi":"रोना","slug":"cry"}},{"tags":{"id":863,"name":"crying","name_en":"Crying","name_hi":"रोना","slug":"crying"}},{"tags":{"id":999,"name":"realization","name_en":"Realization","name_hi":"अहसास","slug":"realization"}},{"tags":{"id":3404,"name":"revealed","name_en":"Revealed","name_hi":"खुलासा","slug":"revealed"}}],"tags":[{"id":862,"name":"break-up","name_en":"Break Up","name_hi":"ब्रेकअप","slug":"break-up"},{"id":10,"name":"cry","name_en":"Cry","name_hi":"रोना","slug":"cry"},{"id":863,"name":"crying","name_en":"Crying","name_hi":"रोना","slug":"crying"},{"id":999,"name":"realization","name_en":"Realization","name_hi":"अहसास","slug":"realization"},{"id":3404,"name":"revealed","name_en":"Revealed","name_hi":"खुलासा","slug":"revealed"}],"updatedAt":"2026-03-23T09:46:48.816Z"}