{"id":1642,"slug":"shweta-tripathi-sharma-closes-her-eyes-in-contemplation-1775128735297","title":"Shweta Tripathi Sharma Closes Her Eyes in Contemplation","title_hi":"श्वेता त्रिपाठी शर्मा ने ध्यान में आंखें बंद कीं","image_url":"https://raw.githubusercontent.com/askgifdotcom/askgifdotcom.github.io/refs/heads/main/gifs/1642.gif","watermarked_url":null,"thumbnail_url":"https://raw.githubusercontent.com/askgifdotcom/askgifdotcom.github.io/refs/heads/main/gifs/thumbnails/1642.gif","status":"published","language":"en","emotion_tags":[],"view_count":0,"date_created":"2026-04-02T11:18:55.297Z","gif_tags":[{"tags":{"id":58,"name":"actress","name_en":"Actress","name_hi":"अभिनेत्री","slug":"actress"}},{"tags":{"id":65,"name":"bollywood","name_en":"Bollywood","name_hi":"बॉलीवुड","slug":"bollywood"}},{"tags":{"id":2411,"name":"calm","name_en":"Calm","name_hi":"शांत","slug":"calm"}},{"tags":{"id":20716,"name":"contemplation","name_en":null,"name_hi":null,"slug":"contemplation"}},{"tags":{"id":2138,"name":"serene","name_en":"Serene","name_hi":"शांत","slug":"serene"}},{"tags":{"id":23282,"name":"shweta-tripathi-sharma","name_en":null,"name_hi":null,"slug":"shweta-tripathi-sharma"}},{"tags":{"id":18003,"name":"thoughtful","name_en":"Thoughtful","name_hi":"विचारशील","slug":"thoughtful"}}],"tags":[{"id":58,"name":"actress","name_en":"Actress","name_hi":"अभिनेत्री","slug":"actress"},{"id":65,"name":"bollywood","name_en":"Bollywood","name_hi":"बॉलीवुड","slug":"bollywood"},{"id":2411,"name":"calm","name_en":"Calm","name_hi":"शांत","slug":"calm"},{"id":20716,"name":"contemplation","name_en":null,"name_hi":null,"slug":"contemplation"},{"id":2138,"name":"serene","name_en":"Serene","name_hi":"शांत","slug":"serene"},{"id":23282,"name":"shweta-tripathi-sharma","name_en":null,"name_hi":null,"slug":"shweta-tripathi-sharma"},{"id":18003,"name":"thoughtful","name_en":"Thoughtful","name_hi":"विचारशील","slug":"thoughtful"}],"related":[{"id":1611,"slug":"suhana-khan-sits-confidently-with-a-calm-expression-at-an-event-1774967597057","title":"Suhana Khan Sits Confidently With a Calm Expression at an Event","title_hi":"सुखाना खान एक कार्यक्रम में शांत भाव के साथ बैठी हैं","image_url":"https://raw.githubusercontent.com/askgifdotcom/askgifdotcom.github.io/refs/heads/main/gifs/1611.gif","watermarked_url":null,"thumbnail_url":"https://raw.githubusercontent.com/askgifdotcom/askgifdotcom.github.io/refs/heads/main/gifs/thumbnails/1611.gif","tags":[]},{"id":1573,"slug":"aditi-sharma-stirs-a-pot-while-deep-in-thought-1774544120293","title":"Aditi Sharma Stirs a Pot While Deep in Thought","title_hi":"अदिति शर्मा गहरे विचार में एक बर्तन में चम्मच चला रही हैं","image_url":"https://raw.githubusercontent.com/askgifdotcom/askgifdotcom.github.io/refs/heads/main/gifs/1573.gif","watermarked_url":null,"thumbnail_url":"https://raw.githubusercontent.com/askgifdotcom/askgifdotcom.github.io/refs/heads/main/gifs/thumbnails/1573.gif","tags":[]},{"id":1539,"slug":"florence-pugh-gives-a-thoughtful-stare-deep-in-contemplation-1774537608608","title":"Florence Pugh Gives a Thoughtful Stare, Deep in Contemplation","title_hi":"फ्लोरेंस प्यू गहरी सोच में एक विचारशील नज़र देती हैं","image_url":"https://raw.githubusercontent.com/askgifdotcom/askgifdotcom.github.io/refs/heads/main/gifs/1539.gif","watermarked_url":null,"thumbnail_url":"https://raw.githubusercontent.com/askgifdotcom/askgifdotcom.github.io/refs/heads/main/gifs/thumbnails/1539.gif","tags":[]},{"id":1537,"slug":"kajal-aggarwal-looks-thoughtful-while-staring-off-into-the-distance-1774537604366","title":"Kajal Aggarwal Looks Thoughtful While Staring Off Into the Distance","title_hi":"काजल अग्रवाल दूर देखते हुए विचारशील लग रही हैं","image_url":"https://raw.githubusercontent.com/askgifdotcom/askgifdotcom.github.io/refs/heads/main/gifs/1537.gif","watermarked_url":null,"thumbnail_url":"https://raw.githubusercontent.com/askgifdotcom/askgifdotcom.github.io/refs/heads/main/gifs/thumbnails/1537.gif","tags":[]},{"id":1513,"slug":"sobhita-dhulipala-thoughtful-reaction-gif-1774531141352","title":"Sobhita Dhulipala Thoughtful Reaction GIF","title_hi":null,"image_url":"https://raw.githubusercontent.com/askgifdotcom/askgifdotcom.github.io/refs/heads/main/gifs/1513.gif","watermarked_url":null,"thumbnail_url":"https://raw.githubusercontent.com/askgifdotcom/askgifdotcom.github.io/refs/heads/main/gifs/thumbnails/1513.gif","tags":[]},{"id":1476,"slug":"a-young-woman-looks-thoughtfully-in-a-serene-environment-1774399668181","title":"A young woman looks thoughtfully in a serene environment.","title_hi":"एक युवा महिला शांत वातावरण में विचारशीलता से देख रही है।","image_url":"https://raw.githubusercontent.com/askgifdotcom/askgifdotcom.github.io/refs/heads/main/gifs/1476.gif","watermarked_url":null,"thumbnail_url":"https://raw.githubusercontent.com/askgifdotcom/askgifdotcom.github.io/refs/heads/main/gifs/thumbnails/1476.gif","tags":[]}],"updatedAt":"2026-04-02T11:19:18.305Z"}