{"id":441,"slug":"wishing-all-the-engineers-out-there-a-happy-engineer-day","title":"Wishing all the engineers out there a happy engineer day.","title_hi":"सभी इंजीनियरों को एक खुश इंजीनियर दिन की शुभकामनाएं।","image_url":"https://raw.githubusercontent.com/askgifdotcom/askgifdotcom.github.io/refs/heads/main/gifs/441.gif","watermarked_url":null,"thumbnail_url":"https://raw.githubusercontent.com/askgifdotcom/askgifdotcom.github.io/refs/heads/main/gifs/thumbnails/wishing-all-the-engineers-out-there-a-happy-engineer-day.gif","status":"published","language":"en","emotion_tags":["wholesome","happy"],"view_count":0,"date_created":"2018-09-15T11:33:52.644Z","gif_tags":[{"tags":{"id":1310,"name":"engineer","name_en":"Engineer","name_hi":"इंजीनियर","slug":"engineer"}},{"tags":{"id":1162,"name":"engineering","name_en":"Engineering","name_hi":"इंजीनियरिंग","slug":"engineering"}},{"tags":{"id":1311,"name":"engineers-day","name_en":"Engineers Day","name_hi":"इंजीनियर्स डे","slug":"engineers-day"}},{"tags":{"id":157,"name":"fail","name_en":"Fail","name_hi":"फेल","slug":"fail"}},{"tags":{"id":1312,"name":"safety-first","name_en":"Safety First","name_hi":"सुरक्षा पहले","slug":"safety-first"}}],"tags":[{"id":1310,"name":"engineer","name_en":"Engineer","name_hi":"इंजीनियर","slug":"engineer"},{"id":1162,"name":"engineering","name_en":"Engineering","name_hi":"इंजीनियरिंग","slug":"engineering"},{"id":1311,"name":"engineers-day","name_en":"Engineers Day","name_hi":"इंजीनियर्स डे","slug":"engineers-day"},{"id":157,"name":"fail","name_en":"Fail","name_hi":"फेल","slug":"fail"},{"id":1312,"name":"safety-first","name_en":"Safety First","name_hi":"सुरक्षा पहले","slug":"safety-first"}],"updatedAt":"2026-03-23T09:48:58.589Z"}