{"id":515,"slug":"when-you-know-only-one-person-at-a-party","title":"When you know only one person at a party.","title_hi":"जब आप किसी पार्टी में केवल एक व्यक्ति को जानते हैं।","image_url":"https://raw.githubusercontent.com/askgifdotcom/askgifdotcom.github.io/refs/heads/main/gifs/515.gif","watermarked_url":null,"thumbnail_url":"https://raw.githubusercontent.com/askgifdotcom/askgifdotcom.github.io/refs/heads/main/gifs/thumbnails/when-you-know-only-one-person-at-a-party.gif","status":"published","language":"en","emotion_tags":["awkward","relatable"],"view_count":0,"date_created":"2019-02-02T05:16:12.463Z","gif_tags":[{"tags":{"id":614,"name":"alone","name_en":"Alone","name_hi":"अकेला","slug":"alone"}},{"tags":{"id":349,"name":"baby","name_en":"Baby","name_hi":"बच्चा","slug":"baby"}},{"tags":{"id":1680,"name":"baby-panda","name_en":"Baby Panda","name_hi":"बेबी पांडा","slug":"baby-panda"}},{"tags":{"id":1681,"name":"clingy","name_en":"Clingy","name_hi":"चिपकू","slug":"clingy"}},{"tags":{"id":166,"name":"cute","name_en":"Cute","name_hi":"क्यूट","slug":"cute"}},{"tags":{"id":1682,"name":"dont-go","name_en":"Dont Go","name_hi":"मत जाओ","slug":"dont-go"}},{"tags":{"id":60,"name":"panda","name_en":"Panda","name_hi":"पांडा","slug":"panda"}}],"tags":[{"id":614,"name":"alone","name_en":"Alone","name_hi":"अकेला","slug":"alone"},{"id":349,"name":"baby","name_en":"Baby","name_hi":"बच्चा","slug":"baby"},{"id":1680,"name":"baby-panda","name_en":"Baby Panda","name_hi":"बेबी पांडा","slug":"baby-panda"},{"id":1681,"name":"clingy","name_en":"Clingy","name_hi":"चिपकू","slug":"clingy"},{"id":166,"name":"cute","name_en":"Cute","name_hi":"क्यूट","slug":"cute"},{"id":1682,"name":"dont-go","name_en":"Dont Go","name_hi":"मत जाओ","slug":"dont-go"},{"id":60,"name":"panda","name_en":"Panda","name_hi":"पांडा","slug":"panda"}],"updatedAt":"2026-03-23T09:48:48.422Z"}