{"id":548,"slug":"when-the-intern-says-that-she-can-handle-the-project-on-her-own","title":"When the intern says that she can handle the project on her own.","title_hi":"जब इंटर्न कहता है कि वह अपने दम पर प्रोजेक्ट को संभाल सकती है।","image_url":"https://raw.githubusercontent.com/askgifdotcom/askgifdotcom.github.io/refs/heads/main/gifs/548.gif","watermarked_url":null,"thumbnail_url":"https://raw.githubusercontent.com/askgifdotcom/askgifdotcom.github.io/refs/heads/main/gifs/thumbnails/when-the-intern-says-that-she-can-handle-the-project-on-her-own.gif","status":"published","language":"en","emotion_tags":["savage","chaotic"],"view_count":0,"date_created":"2019-02-23T11:55:26.581Z","gif_tags":[{"tags":{"id":58,"name":"actress","name_en":"Actress","name_hi":"अभिनेत्री","slug":"actress"}},{"tags":{"id":593,"name":"american","name_en":"American","name_hi":"अमेरिकी","slug":"american"}},{"tags":{"id":1828,"name":"as-if","name_en":"As If","name_hi":"जैसे कि","slug":"as-if"}},{"tags":{"id":809,"name":"blonde","name_en":"Blonde","name_hi":"ब्लॉन्ड","slug":"blonde"}},{"tags":{"id":1829,"name":"cheerleader","name_en":"Cheerleader","name_hi":"चीयरलीडर","slug":"cheerleader"}},{"tags":{"id":7,"name":"intern","name_en":"Intern","name_hi":"इंटर्न","slug":"intern"}},{"tags":{"id":1830,"name":"jordyn-jones","name_en":"Jordyn Jones","name_hi":"जॉर्डिन जोन्स","slug":"jordyn-jones"}},{"tags":{"id":636,"name":"model","name_en":"Model","name_hi":"मॉडल","slug":"model"}},{"tags":{"id":1831,"name":"overnight","name_en":"Overnight","name_hi":"रातोंरात","slug":"overnight"}},{"tags":{"id":1832,"name":"sarcastic","name_en":"Sarcastic","name_hi":"व्यंग्यात्मक","slug":"sarcastic"}},{"tags":{"id":256,"name":"singer","name_en":"Singer","name_hi":"गायक","slug":"singer"}},{"tags":{"id":486,"name":"tv-show","name_en":"Tv Show","name_hi":"टीवी शो","slug":"tv-show"}},{"tags":{"id":1281,"name":"youtuber","name_en":"Youtuber","name_hi":"यूट्यूबर","slug":"youtuber"}}],"tags":[{"id":58,"name":"actress","name_en":"Actress","name_hi":"अभिनेत्री","slug":"actress"},{"id":593,"name":"american","name_en":"American","name_hi":"अमेरिकी","slug":"american"},{"id":1828,"name":"as-if","name_en":"As If","name_hi":"जैसे कि","slug":"as-if"},{"id":809,"name":"blonde","name_en":"Blonde","name_hi":"ब्लॉन्ड","slug":"blonde"},{"id":1829,"name":"cheerleader","name_en":"Cheerleader","name_hi":"चीयरलीडर","slug":"cheerleader"},{"id":7,"name":"intern","name_en":"Intern","name_hi":"इंटर्न","slug":"intern"},{"id":1830,"name":"jordyn-jones","name_en":"Jordyn Jones","name_hi":"जॉर्डिन जोन्स","slug":"jordyn-jones"},{"id":636,"name":"model","name_en":"Model","name_hi":"मॉडल","slug":"model"},{"id":1831,"name":"overnight","name_en":"Overnight","name_hi":"रातोंरात","slug":"overnight"},{"id":1832,"name":"sarcastic","name_en":"Sarcastic","name_hi":"व्यंग्यात्मक","slug":"sarcastic"},{"id":256,"name":"singer","name_en":"Singer","name_hi":"गायक","slug":"singer"},{"id":486,"name":"tv-show","name_en":"Tv Show","name_hi":"टीवी शो","slug":"tv-show"},{"id":1281,"name":"youtuber","name_en":"Youtuber","name_hi":"यूट्यूबर","slug":"youtuber"}],"updatedAt":"2026-03-23T09:48:43.893Z"}