{"id":64,"slug":"when-you-can-see-your-goal-nearby","title":"When you can see your goal nearby.","title_hi":"जब आप अपना लक्ष्य पास में देख सकते हैं।","image_url":"https://raw.githubusercontent.com/askgifdotcom/askgifdotcom.github.io/refs/heads/main/gifs/64.gif","watermarked_url":null,"thumbnail_url":"https://raw.githubusercontent.com/askgifdotcom/askgifdotcom.github.io/refs/heads/main/gifs/thumbnails/when-you-can-see-your-goal-nearby.gif","status":"published","language":"en","emotion_tags":["hyped","happy"],"view_count":0,"date_created":"2018-05-26T08:34:02.512Z","gif_tags":[{"tags":{"id":61,"name":"child","name_en":"Child","name_hi":"बच्चा","slug":"child"}},{"tags":{"id":81,"name":"funny","name_en":"Funny","name_hi":"फनी","slug":"funny"}},{"tags":{"id":35,"name":"innocent","name_en":"Innocent","name_hi":"निर्दोष","slug":"innocent"}},{"tags":{"id":63,"name":"kid","name_en":"Kid","name_hi":"बच्चा","slug":"kid"}},{"tags":{"id":99,"name":"spray","name_en":"Spray","name_hi":"स्प्रे","slug":"spray"}}],"tags":[{"id":61,"name":"child","name_en":"Child","name_hi":"बच्चा","slug":"child"},{"id":81,"name":"funny","name_en":"Funny","name_hi":"फनी","slug":"funny"},{"id":35,"name":"innocent","name_en":"Innocent","name_hi":"निर्दोष","slug":"innocent"},{"id":63,"name":"kid","name_en":"Kid","name_hi":"बच्चा","slug":"kid"},{"id":99,"name":"spray","name_en":"Spray","name_hi":"स्प्रे","slug":"spray"}],"updatedAt":"2026-03-23T09:49:50.365Z"}