{"id":843,"slug":"schools-in-a-nutshell","title":"Schools in a nutshell.","title_hi":"संक्षेप में स्कूल।","image_url":"https://raw.githubusercontent.com/askgifdotcom/askgifdotcom.github.io/refs/heads/main/gifs/843.gif","watermarked_url":null,"thumbnail_url":"https://raw.githubusercontent.com/askgifdotcom/askgifdotcom.github.io/refs/heads/main/gifs/thumbnails/schools-in-a-nutshell.gif","status":"published","language":"en","emotion_tags":["relatable","chaotic"],"view_count":0,"date_created":"2019-08-07T18:10:19.741Z","gif_tags":[{"tags":{"id":1425,"name":"animation","name_en":"Animation","name_hi":"एनिमेशन","slug":"animation"}},{"tags":{"id":1115,"name":"anime","name_en":"Anime","name_hi":"एनीमे","slug":"anime"}},{"tags":{"id":2879,"name":"books","name_en":"Books","name_hi":"किताबें","slug":"books"}},{"tags":{"id":282,"name":"cartoon","name_en":"Cartoon","name_hi":"कार्टून","slug":"cartoon"}},{"tags":{"id":3237,"name":"force","name_en":"Force","name_hi":"शक्ति","slug":"force"}},{"tags":{"id":3238,"name":"forced","name_en":"Forced","name_hi":"जबरदस्ती","slug":"forced"}},{"tags":{"id":3239,"name":"learning","name_en":"Learning","name_hi":"सीखना","slug":"learning"}},{"tags":{"id":1183,"name":"school","name_en":"School","name_hi":"स्कूल","slug":"school"}}],"tags":[{"id":1425,"name":"animation","name_en":"Animation","name_hi":"एनिमेशन","slug":"animation"},{"id":1115,"name":"anime","name_en":"Anime","name_hi":"एनीमे","slug":"anime"},{"id":2879,"name":"books","name_en":"Books","name_hi":"किताबें","slug":"books"},{"id":282,"name":"cartoon","name_en":"Cartoon","name_hi":"कार्टून","slug":"cartoon"},{"id":3237,"name":"force","name_en":"Force","name_hi":"शक्ति","slug":"force"},{"id":3238,"name":"forced","name_en":"Forced","name_hi":"जबरदस्ती","slug":"forced"},{"id":3239,"name":"learning","name_en":"Learning","name_hi":"सीखना","slug":"learning"},{"id":1183,"name":"school","name_en":"School","name_hi":"स्कूल","slug":"school"}],"updatedAt":"2026-03-23T09:48:03.344Z"}