{"page":1,"total":1,"pageSize":24,"gifs":[{"id":577,"slug":"when-your-mom-is-beating-you-and-all-of-a-sudden-you-got-visitors","title":"When your mom is beating you and all of a sudden you got visitors.","title_hi":"जब आपकी माँ आपको पीट रही है और अचानक आपको आगंतुक मिल गए।","image_url":"https://raw.githubusercontent.com/askgifdotcom/askgifdotcom.github.io/refs/heads/main/gifs/577.gif","watermarked_url":null,"thumbnail_url":"https://raw.githubusercontent.com/askgifdotcom/askgifdotcom.github.io/refs/heads/main/gifs/thumbnails/when-your-mom-is-beating-you-and-all-of-a-sudden-you-got-visitors.gif","tags":[{"id":2,"name":"actor","name_en":"Actor","name_hi":"अभिनेता","slug":"actor"},{"id":460,"name":"beat","name_en":"Beat","name_hi":"बीट","slug":"beat"},{"id":1981,"name":"beating","name_en":"Beating","name_hi":"पीटना","slug":"beating"},{"id":1982,"name":"bill-hader","name_en":"Bill Hader","name_hi":"बिल हैडर","slug":"bill-hader"},{"id":903,"name":"comedian","name_en":"Comedian","name_hi":"कॉमेडियन","slug":"comedian"},{"id":863,"name":"crying","name_en":"Crying","name_hi":"रोना","slug":"crying"},{"id":904,"name":"director","name_en":"Director","name_hi":"निर्देशक","slug":"director"},{"id":1151,"name":"laugh-cry","name_en":"Laugh Cry","name_hi":"हंसना रोना","slug":"laugh-cry"},{"id":1940,"name":"laughing","name_en":"Laughing","name_hi":"हंसना","slug":"laughing"},{"id":457,"name":"mom","name_en":"Mom","name_hi":"माँ","slug":"mom"},{"id":458,"name":"mother","name_en":"Mother","name_hi":"माता","slug":"mother"},{"id":829,"name":"producer","name_en":"Producer","name_hi":"निर्माता","slug":"producer"},{"id":1345,"name":"saturday-night-live","name_en":"Saturday Night Live","name_hi":"सैटरडे नाइट लाइव","slug":"saturday-night-live"},{"id":1346,"name":"snl","name_en":"Snl","name_hi":"एसएनएल","slug":"snl"},{"id":909,"name":"writer","name_en":"Writer","name_hi":"लेखक","slug":"writer"}]}],"personName":"Bill Hader","personNameHi":null,"updatedAt":"2026-03-26T10:07:26.016Z"}