{"page":1,"total":2,"pageSize":24,"tagSlug":"bag","gifs":[{"id":831,"slug":"when-girls-come-to-know-that-you-have-a-mature-and-sporty-bag","title":"When girls come to know that you have a mature and sporty bag.","title_hi":"जब लड़कियों को पता चलता है कि आपके पास एक परिपक्व और स्पोर्टी बैग है।","image_url":"https://raw.githubusercontent.com/askgifdotcom/askgifdotcom.github.io/refs/heads/main/gifs/831.gif","watermarked_url":null,"thumbnail_url":"https://raw.githubusercontent.com/askgifdotcom/askgifdotcom.github.io/refs/heads/main/gifs/thumbnails/when-girls-come-to-know-that-you-have-a-mature-and-sporty-bag.gif","tags":[{"id":1466,"name":"angels","name_en":"Angels","name_hi":"फरिश्ते","slug":"angels"},{"id":2968,"name":"bag","name_en":"Bag","name_hi":"बैग","slug":"bag"},{"id":443,"name":"bikini","name_en":"Bikini","name_hi":"बिकिनी","slug":"bikini"},{"id":1006,"name":"fashion-model","name_en":"Fashion Model","name_hi":"फैशन मॉडल","slug":"fashion-model"},{"id":2731,"name":"fashion-show","name_en":"Fashion Show","name_hi":"फैशन शो","slug":"fashion-show"},{"id":66,"name":"hot","name_en":"Hot","name_hi":"गर्म","slug":"hot"},{"id":2478,"name":"lingerie","name_en":"Lingerie","name_hi":"अंडरवियर","slug":"lingerie"},{"id":3190,"name":"mature","name_en":"Mature","name_hi":"परिपक्व","slug":"mature"},{"id":3191,"name":"mature-bag","name_en":"Mature Bag","name_hi":"परिपक्व बैग","slug":"mature-bag"},{"id":3192,"name":"models","name_en":"Models","name_hi":"मॉडल","slug":"models"},{"id":292,"name":"sexy","name_en":"Sexy","name_hi":"सेक्सी","slug":"sexy"},{"id":3193,"name":"sporty","name_en":"Sporty","name_hi":"खेलकूद","slug":"sporty"},{"id":3194,"name":"sporty-bag","name_en":"Sporty Bag","name_hi":"खेलकूद बैग","slug":"sporty-bag"},{"id":1259,"name":"super-model","name_en":"Super Model","name_hi":"सुपर मॉडल","slug":"super-model"},{"id":1473,"name":"victoria-secrets","name_en":"Victoria Secrets","name_hi":"विक्टोरिया सीक्रेट्स","slug":"victoria-secrets"},{"id":3195,"name":"victorias-angels","name_en":"Victorias Angels","name_hi":"विक्टोरियाज एंजेल्स","slug":"victorias-angels"},{"id":1008,"name":"victorias-secret","name_en":"Victorias Secret","name_hi":"विक्टोरियाज सीक्रेट","slug":"victorias-secret"}]},{"id":777,"slug":"rahul-gandhi-after-election-results","title":"Rahul Gandhi after election results.","title_hi":"चुनाव नतीजों के बाद राहुल गांधी","image_url":"https://raw.githubusercontent.com/askgifdotcom/askgifdotcom.github.io/refs/heads/main/gifs/777.gif","watermarked_url":null,"thumbnail_url":"https://raw.githubusercontent.com/askgifdotcom/askgifdotcom.github.io/refs/heads/main/gifs/thumbnails/rahul-gandhi-after-election-results.gif","tags":[{"id":1670,"name":"2019-general-election","name_en":"2019 General Election","name_hi":"2019 आम चुनाव","slug":"2019-general-election"},{"id":2968,"name":"bag","name_en":"Bag","name_hi":"बैग","slug":"bag"},{"id":2969,"name":"coward","name_en":"Coward","name_hi":"कायर","slug":"coward"},{"id":447,"name":"difficult","name_en":"Difficult","name_hi":"कठिन","slug":"difficult"},{"id":2964,"name":"election-results","name_en":"Election Results","name_hi":"चुनाव परिणाम","slug":"election-results"},{"id":2970,"name":"modi-again","name_en":"Modi Again","name_hi":"मोदी फिर से","slug":"modi-again"},{"id":2971,"name":"pack","name_en":"Pack","name_hi":"पैक","slug":"pack"},{"id":2972,"name":"packing","name_en":"Packing","name_hi":"पैकिंग","slug":"packing"},{"id":705,"name":"politician","name_en":"Politician","name_hi":"राजनेता","slug":"politician"},{"id":719,"name":"politics","name_en":"Politics","name_hi":"राजनीति","slug":"politics"},{"id":2973,"name":"rahul-gandhi","name_en":"Rahul Gandhi","name_hi":"राहुल गांधी","slug":"rahul-gandhi"},{"id":795,"name":"struggle","name_en":"Struggle","name_hi":"संघर्ष","slug":"struggle"},{"id":2967,"name":"tsunamo","name_en":"Tsunamo","name_hi":"तूफान","slug":"tsunamo"}]}],"updatedAt":"2026-03-23T08:54:56.324Z"}